edx_helper/__init__.py
edx_helper/common.py
edx_helper/edx_dl.py
edx_helper/parsing.py
edx_helper/utils.py
edx_helper-0.6.5.dist-info/METADATA
edx_helper-0.6.5.dist-info/WHEEL
edx_helper-0.6.5.dist-info/entry_points.txt
edx_helper-0.6.5.dist-info/licenses/LICENSE
edx_helper-0.6.5.dist-info/RECORD
