Metadata-Version: 2.1
Name: edx-helper
Version: 0.6.5
Summary: Simple tool to download video and lecture materials from edx.org.
Project-URL: Homepage, https://github.com/csyezheng/edx-helper
Maintainer-email: Ye Zheng <csyezheng@gmail.com>
License:                    GNU LESSER GENERAL PUBLIC LICENSE
License-File: LICENSE
Keywords: MOOCs,download,edX,edX-dl,education,video
Classifier: Development Status :: 4 - Beta
Classifier: Environment :: Console
Classifier: Intended Audience :: End Users/Desktop
Classifier: License :: OSI Approved :: GNU Lesser General Public License v3 or later (LGPLv3+)
Classifier: Operating System :: OS Independent
Classifier: Programming Language :: Python
Classifier: Programming Language :: Python :: 3
Classifier: Programming Language :: Python :: 3.7
Classifier: Programming Language :: Python :: 3.8
Classifier: Programming Language :: Python :: 3.9
Classifier: Programming Language :: Python :: 3.10
Classifier: Programming Language :: Python :: 3.11
Classifier: Programming Language :: Python :: Implementation :: CPython
Classifier: Programming Language :: Python :: Implementation :: PyPy
Classifier: Topic :: Education
Requires-Dist: beautifulsoup4>=4.6.0
Requires-Dist: html5lib>=1.0.1
Requires-Dist: requests>=2.18.4
Requires-Dist: six>=1.11.0
Requires-Dist: tqdm>=4.66.1
Requires-Dist: youtube-dl>=2021.12.17
Provides-Extra: dev
Requires-Dist: coverage>=3.7; extra == 'dev'
Requires-Dist: mock>=1.0.1; extra == 'dev'
Requires-Dist: pandoc; extra == 'dev'
Requires-Dist: pytest-cov; extra == 'dev'
Requires-Dist: pytest-xdist; extra == 'dev'
Requires-Dist: pytest>=2.5; extra == 'dev'
Requires-Dist: tox; extra == 'dev'
